loggers/__init__.py
loggers/loggers.py
decorated_logger-1.0.0.dist-info/METADATA
decorated_logger-1.0.0.dist-info/WHEEL
decorated_logger-1.0.0.dist-info/top_level.txt
decorated_logger-1.0.0.dist-info/RECORD
