Metadata-Version: 2.1
Name: decorated_logger
Version: 1.0.0
Summary: A Python library for logging function calls and results to the console or a file with optional text decoration.
Author: Daniel Stefanov
